invenio_curations/__init__.py
invenio_curations/config.py
invenio_curations/ext.py
invenio_curations/proxies.py
invenio_curations/searchapp.py
invenio_curations/tasks.py
invenio_curations/webpack.py
invenio_curations/assets/semantic-ui/js/invenio_curations/deposit/CurationRequestForm.js
invenio_curations/assets/semantic-ui/js/invenio_curations/deposit/CustomDepositStatusBox.js
invenio_curations/assets/semantic-ui/js/invenio_curations/deposit/DepositBox.js
invenio_curations/assets/semantic-ui/js/invenio_curations/deposit/RequestOrPublishButton.js
invenio_curations/assets/semantic-ui/js/invenio_curations/deposit/StatusDisplay.js
invenio_curations/assets/semantic-ui/js/invenio_curations/deposit/index.js
invenio_curations/assets/semantic-ui/js/invenio_curations/deposit/utils.js
invenio_curations/assets/semantic-ui/js/invenio_curations/deposit/withCurationStatus.js
invenio_curations/assets/semantic-ui/js/invenio_curations/requests/Buttons.js
invenio_curations/assets/semantic-ui/js/invenio_curations/requests/Icons.js
invenio_curations/assets/semantic-ui/js/invenio_curations/requests/ModalTriggers.js
invenio_curations/assets/semantic-ui/js/invenio_curations/requests/RequestFeed.js
invenio_curations/assets/semantic-ui/js/invenio_curations/requests/RequestMetadataLayout.js
invenio_curations/assets/semantic-ui/js/invenio_curations/requests/Status.js
invenio_curations/assets/semantic-ui/js/invenio_curations/requests/StatusLabel.js
invenio_curations/assets/semantic-ui/js/invenio_curations/requests/TypeLabel.js
invenio_curations/assets/semantic-ui/js/invenio_curations/requests/index.js
invenio_curations/assets/semantic-ui/js/invenio_curations/requests/timelineActionEvents.js
invenio_curations/assets/semantic-ui/translations/invenio_curations/i18next-scanner.config.js
invenio_curations/assets/semantic-ui/translations/invenio_curations/i18next.js
invenio_curations/assets/semantic-ui/translations/invenio_curations/package-lock.json
invenio_curations-0.5.0.dist-info/licenses/AUTHORS.rst
invenio_curations-0.5.0.dist-info/licenses/LICENSE
invenio_curations-0.5.0.dist-info/METADATA
invenio_curations-0.5.0.dist-info/WHEEL
invenio_curations-0.5.0.dist-info/entry_points.txt
invenio_curations-0.5.0.dist-info/top_level.txt
invenio_curations-0.5.0.dist-info/RECORD
