Metadata-Version: 2.4
Name: invenio-curations
Version: 0.5.0
Summary: "Invenio module for generic and customizable curations."
Home-page: https://github.com/tu-graz-library/invenio-curations
Author: Graz University of Technology
Author-email: info@tugraz.at
License: MIT
Keywords: invenio curations
Platform: any
Classifier: Development Status :: 5 - Production/Stable
Classifier: Programming Language :: Python :: 3.12
Requires-Python: >=3.12
License-File: LICENSE
License-File: AUTHORS.rst
Requires-Dist: invenio-drafts-resources>=3.0.0
Requires-Dist: invenio-rdm-records>=19.0.0
Requires-Dist: invenio-requests>=4.1.0
Requires-Dist: nh3>=0.2.0
Provides-Extra: tests
Requires-Dist: invenio-app<3.0.0,>=2.0.0; extra == "tests"
Requires-Dist: invenio-app-rdm<14.0.0,>=13.0.0b4.dev1; extra == "tests"
Requires-Dist: invenio-db[mysql,postgresql]<3.0.0,>=2.0.0; extra == "tests"
Requires-Dist: invenio-search[opensearch2]<4.0.0,>=3.0.0; extra == "tests"
Requires-Dist: pytest-black>=0.6.0; extra == "tests"
Requires-Dist: pytest-invenio<4.0.0,>=3.0.0; extra == "tests"
Requires-Dist: sphinx>=4.5.0; extra == "tests"
Requires-Dist: types-flask>=1.1.6; extra == "tests"
Requires-Dist: ruff>=0.1.0; extra == "tests"
Requires-Dist: mypy>=1.15.0; extra == "tests"
Requires-Dist: types-setuptools>=78.1.0; extra == "tests"
Provides-Extra: opensearch1
Requires-Dist: invenio-search[opensearch1]<4.0.0,>=3.0.0; extra == "opensearch1"
Provides-Extra: opensearch2
Requires-Dist: invenio-search[opensearch2]<4.0.0,>=3.0.0; extra == "opensearch2"
Dynamic: license-file
